space_analysis-2024.11.11.dist-info/METADATA
space_analysis-2024.11.11.dist-info/WHEEL
space_analysis-2024.11.11.dist-info/entry_points.txt
space_analysis-2024.11.11.dist-info/licenses/LICENSE
space_analysis/__init__.py
space_analysis/_modidx.py
space_analysis/core.py
space_analysis/ds/__init__.py
space_analysis/ds/config.py
space_analysis/ds/spz/__init__.py
space_analysis/ds/spz/io.py
space_analysis/ds/spz/plot.py
space_analysis/ds/spz/utils.py
space_analysis/ds/tplot/__init__.py
space_analysis/ds/tplot/formulary.py
space_analysis/ds/tplot/plot.py
space_analysis/ds/tplot/trans.py
space_analysis/ds/tplot/utils.py
space_analysis/ds/ts/__init__.py
space_analysis/ds/ts/io.py
space_analysis/ds/ts/plot.py
space_analysis/ds/ts/utils.py
space_analysis/io/__init__.py
space_analysis/io/cdf.py
space_analysis/meta.py
space_analysis/missions/__init__.py
space_analysis/missions/dscovr/__init__.py
space_analysis/missions/juno/__init__.py
space_analysis/missions/juno/fgm.py
space_analysis/missions/psp.py
space_analysis/missions/solo/__init__.py
space_analysis/missions/stereo/__init__.py
space_analysis/missions/themis/__init__.py
space_analysis/missions/wind/__init__.py
space_analysis/missions/wind/mag.py
space_analysis/missions/wind/plasma.py
space_analysis/plasma/__init__.py
space_analysis/plasma/formulary/__init__.py
space_analysis/plasma/formulary/numpy.py
space_analysis/plasma/formulary/polars.py
space_analysis/plasma/mhd_waves.py
space_analysis/plot/__init__.py
space_analysis/plot/basic.py
space_analysis/simulation/__init__.py
space_analysis/simulation/warpx.py
space_analysis/utils/__init__.py
space_analysis/utils/basic.py
space_analysis/utils/cdas.py
space_analysis/utils/lbl.py
space_analysis/utils/math.py
space_analysis/utils/mission.py
space_analysis/utils/pds.py
space_analysis/utils/speasy.py
space_analysis-2024.11.11.dist-info/RECORD
