Metadata-Version: 2.1
Name: space-analysis
Version: 2024.11.11
Summary: Python library for data analysis in space physics
Author-Email: Beforerr <zzj956959688@gmail.com>
Project-URL: Homepage, https://beforerr.github.io/space-analysis.py
Project-URL: Repository, https://github.com/beforerr/space-analysis.py
Requires-Python: >=3.10
Requires-Dist: beforerr
Requires-Dist: pydantic
Requires-Dist: plum-dispatch
Requires-Dist: polars
Requires-Dist: plasmapy
Requires-Dist: astropy
Requires-Dist: loguru
Requires-Dist: rich
Requires-Dist: humanize
Provides-Extra: plot
Requires-Dist: hvplot; extra == "plot"
Provides-Extra: io
Requires-Dist: pyspedas; extra == "io"
Requires-Dist: speasy; extra == "io"
Requires-Dist: pycdfpp; extra == "io"
Requires-Dist: cdasws; extra == "io"
Requires-Dist: pdr; extra == "io"
Requires-Dist: pooch; extra == "io"
Provides-Extra: dev
Requires-Dist: ipykernel; extra == "dev"
Requires-Dist: nbdev; extra == "dev"
Requires-Dist: jupyter-cache; extra == "dev"
Provides-Extra: doc
Requires-Dist: itables; extra == "doc"
Requires-Dist: great_tables; extra == "doc"
